vsapy/.DS_Store
vsapy/__init__.py
vsapy/bag.py
vsapy/bsc.py
vsapy/bsc_stats.py
vsapy/cspvec.py
vsapy/helpers.py
vsapy/hrr.py
vsapy/laiho.py
vsapy/laihox.py
vsapy/logger_utils.py
vsapy/role_vectors.py
vsapy/sparse_stats.py
vsapy/tern.py
vsapy/ternzero.py
vsapy/vsa_stats.py
vsapy/vsa_tokenizer.py
vsapy/vsapy.py
vsapy/vsatype.py
vsapy-0.9.0.dist-info/LICENSE
vsapy-0.9.0.dist-info/WHEEL
vsapy-0.9.0.dist-info/METADATA
vsapy-0.9.0.dist-info/RECORD
