Metadata-Version: 2.1
Name: vsapy
Version: 0.9.0
Summary: Vector Symbolic Architecture(VSA) library that allows building VSA apps that use various flavours of VSA vectors.
Home-page: https://github.com/vsapy/vsapy
License: MIT
Author: Chris Simpkin
Requires-Python: >=3.8,<3.11
Classifier: License :: OSI Approved :: MIT License
Classifier: Programming Language :: Python :: 3
Classifier: Programming Language :: Python :: 3.8
Classifier: Programming Language :: Python :: 3.9
Classifier: Programming Language :: Python :: 3.10
Requires-Dist: Pillow (>=9.1.1,<10.0.0)
Requires-Dist: colorama (>=0.4.5,<0.5.0)
Requires-Dist: gmpy2 (>=2.1.2,<3.0.0)
Requires-Dist: matplotlib (>=3.5.2,<4.0.0)
Requires-Dist: nltk (>=3.7,<4.0)
Requires-Dist: numpy (>=1.22.4,<2.0.0)
Requires-Dist: pandas (>=1.4.2,<2.0.0)
Requires-Dist: python-dateutil (>=2.8.2,<3.0.0)
Requires-Dist: regex (>=2022.4.24,<2023.0.0)
Requires-Dist: scikit-image (>=0.19.3,<0.20.0)
Requires-Dist: scipy (>=1.8.1,<2.0.0)
Requires-Dist: setuptools (>=62.3.2,<63.0.0)
Requires-Dist: six (>=1.16.0,<2.0.0)
Requires-Dist: unicodedata2 (>=14.0.0,<15.0.0)
Requires-Dist: wheel (>=0.37.1,<0.38.0)
Requires-Dist: xmltodict (>=0.13.0,<0.14.0)
Project-URL: Repository, https://github.com/vsapy/vsapy
